{
    "example" : {
        "info" : {
            "name" : "test",
            "description" : "This is a example for what a crewmate could be",
            "_id" : -1234
        },
        "_comment" : "for all buffs and nerfs, the typeOf property should always be either a '+'  or '-' (adds/subtracts the buff/nerf to the attribute), a '*' or '/' (multiplies/divides the buff/nerf by the attribute), or a '^' or '%' (raises the buff/nerf to a power/root) ",
        "stats" : {
            "rarity" : {

            },
            "buff1" : {
                "description" : "buffs attribute buff1",
                "typeOf" : "+",
                "default" : "0"
            },
            "buff2" : {
                "description" : "buffs attribute buff2",
                "typeOf" : "*",
                "default" : "0"
            },
            "buff3" : {
                "description" : "buffs attribute buff3",
                "typeOf" : "^",
                "default" : "0"
            },
            "nerf1" : {
                "description" : "nerfs attribute nerf1",
                "typeOf" : "-",
                "default" : "0"
            },
            "nerf2" : {
                "description" : "nerfs attribute nerf2",
                "typeOf" : "/",
                "default" : "0"
            },
            "nerf3" : {
                "description" : "nerfs attribute nerf3",
                "typeOf" : "%",
                "default" : "0"
            }
        }
    },
    "henry" : {
        "info" : {
            "name" : "henry",
            "description" : "An engineer, henry gives +1 endurance -1 size, but -1 drive skill.",
            "_id" : -1111
        },
        "_comment" : "henry is a basic, common crew mate and gives a boost to endurance but a debuff to skill.",
        "stats" : {
            "rarity" : {
                "common" : "+0 => +25% boost on stats gained per level."
            },
            "buff1" : {
                "description" : "Is good at building things into smaller spaces.",
                "typeOf" : "-1 speed",
                "default" : "1"
            },
            "buff2" : {
                "description" : "is good at building sturdy bots.",
                "typeOf" : "*",
                "default" : "0"
            },
            "buff3" : {
                "description" : "buffs attribute buff3",
                "typeOf" : "^",
                "default" : "0"
            },
            "nerf1" : {
                "description" : "Is bad at driving.",
                "typeOf" : "-1 meanueverability",
                "default" : "-1"
            },
            "nerf2" : {
                "description" : "nerfs attribute nerf2",
                "typeOf" : "/",
                "default" : "0"
            },
            "nerf3" : {
                "description" : "nerfs attribute nerf3",
                "typeOf" : "%",
                "default" : "0"
            }
        }
    }
}
