{
    "battery" : {
        "life" : {
            "default" : 0,
            "desc" : "How long you can control your bot/ how many actions you can make."
        },
        "strength" : {
            "default" : 0,
            "desc" : "Effects wheel speed, arm strength, grip strength, etc."
        }
    },
    "attachmentEx" : {
        "speed" : {
            "default" : 0,
            "desc" : "Effects how quickly your bots attachments can move."
        },
        "strength" : {
            "default" : 0,
            "desc" : "The strength of arms, grips, and speed of wheels."
        },
        "durabitity" : {
            "default" : 0,
            "desc" : "How long an attachment will last before breaking."
        },
        "mass" : {
            "default" : 0,
            "desc" : "How much weight the attachment will have."
        },
        "size" : {
            "default" : 0,
            "desc" : "How clunky the attachment will be."
        },
        "_id" : 1234
    }
}
